instagram_data/__init__.py
instagram_data/app.py
instagram_data/scraper.py
instagram_data-0.0.4.dist-info/METADATA
instagram_data-0.0.4.dist-info/WHEEL
instagram_data-0.0.4.dist-info/entry_points.txt
instagram_data-0.0.4.dist-info/top_level.txt
instagram_data-0.0.4.dist-info/RECORD
