Metadata-Version: 2.1
Name: instagram-data
Version: 0.0.4
Summary: Scrapes the name and followers of 200 of the top Instagram influencers and puts it in array of dictionaries for JS. It also saves their profile pictures in an img folder.
Home-page: https://github.com/ewbyf/instagram-data
Author: ewbyf (Eric Wong)
Author-email: ewbyf@umsystem.edu
License: UNKNOWN
Keywords: instagram,scraper,download,media,followers
Platform: UNKNOWN
Requires-Dist: beautifulsoup4
Requires-Dist: requests
Requires-Dist: instagrapi
Requires-Dist: pillow
